{"mc":{
	"bossexpp":{
		"frameRate":24,
		"events":[
			
			],
		"frames":[
			
			{
			"res":"7F270226",
			"x":147,
			"y":110
			},
			{
			"res":"47321BC1",
			"x":147,
			"y":107
			},
			{
			"res":"98CE00DA",
			"x":146,
			"y":105
			},
			{
			"res":"553F4D05",
			"x":146,
			"y":102
			},
			{
			"res":"D317432A",
			"x":146,
			"y":100
			},
			{
			"res":"1932FFE8",
			"x":146,
			"y":99
			},
			{
			"res":"123309C6",
			"x":146,
			"y":97
			},
			{
			"res":"3911B93D",
			"x":146,
			"y":96
			},
			{
			"res":"CB7D7700",
			"x":146,
			"y":94
			},
			{
			"res":"E688D7D",
			"x":145,
			"y":93
			},
			{
			"res":"5A9B86E6",
			"x":144,
			"y":91
			},
			{
			"res":"2E91D534",
			"x":143,
			"y":89
			},
			{
			"res":"A12A722E",
			"x":142,
			"y":88
			},
			{
			"res":"345874A1",
			"x":141,
			"y":86
			},
			{
			"res":"34C42683",
			"x":140,
			"y":85
			},
			{
			"res":"4EECB0C0",
			"x":139,
			"y":84
			},
			{
			"res":"76A9AD9C",
			"x":138,
			"y":83
			},
			{
			"res":"944E3BD8",
			"x":137,
			"y":82
			},
			{
			"res":"8ED3AFE8",
			"x":136,
			"y":80
			},
			{
			"res":"6C658526",
			"x":135,
			"y":79
			},
			{
			"res":"1FA0A53B",
			"x":135,
			"y":78
			},
			{
			"res":"280EE8E4",
			"x":134,
			"y":77
			},
			{
			"res":"F547EE54",
			"x":134,
			"y":76
			},
			{
			"res":"1B338CA3",
			"x":134,
			"y":74
			},
			{
			"res":"85AD8584",
			"x":133,
			"y":73
			},
			{
			"res":"C7748A84",
			"x":133,
			"y":72
			},
			{
			"res":"C89B689E",
			"x":130,
			"y":70
			},
			{
			"res":"B36FAE0",
			"x":129,
			"y":69
			},
			{
			"res":"A7BCCAF",
			"x":128,
			"y":68
			},
			{
			"res":"A56A841F",
			"x":128,
			"y":67
			},
			{
			"res":"49CF2D80",
			"x":126,
			"y":66
			},
			{
			"res":"8B05478",
			"x":126,
			"y":64
			},
			{
			"res":"533B108C",
			"x":125,
			"y":63
			},
			{
			"res":"86D5947A",
			"x":125,
			"y":62
			},
			{
			"res":"DDAEEEF8",
			"x":125,
			"y":61
			},
			{
			"res":"ED219405",
			"x":125,
			"y":59
			},
			{
			"res":"667F0ED5",
			"x":125,
			"y":58
			},
			{
			"res":"7879F75B",
			"x":125,
			"y":57
			},
			{
			"res":"AA0D704B",
			"x":125,
			"y":56
			},
			{
			"res":"27CC3E8B",
			"x":125,
			"y":55
			}
			]
}},
	"res":{
		"76A9AD9C":{"x":1690,"y":392,"w":222,"h":172},
		"6C658526":{"x":461,"y":392,"w":226,"h":177},
		"7879F75B":{"x":497,"y":1,"w":246,"h":200},
		"A12A722E":{"x":461,"y":571,"w":209,"h":167},
		"A56A841F":{"x":1240,"y":199,"w":237,"h":190},
		"DDAEEEF8":{"x":1240,"y":1,"w":243,"h":196},
		"345874A1":{"x":689,"y":570,"w":212,"h":169},
		"1932FFE8":{"x":1133,"y":738,"w":193,"h":155},
		"98CE00DA":{"x":1518,"y":739,"w":183,"h":148},
		"ED219405":{"x":993,"y":1,"w":245,"h":198},
		"2E91D534":{"x":1461,"y":571,"w":205,"h":166},
		"D317432A":{"x":903,"y":739,"w":191,"h":154},
		"F547EE54":{"x":231,"y":391,"w":228,"h":180},
		"C7748A84":{"x":249,"y":204,"w":229,"h":185},
		"1FA0A53B":{"x":1461,"y":391,"w":227,"h":178},
		"27CC3E8B":{"x":1,"y":1,"w":246,"h":202},
		"5A9B86E6":{"x":1133,"y":572,"w":203,"h":164},
		"C89B689E":{"x":497,"y":203,"w":233,"h":187},
		"47321BC1":{"x":1703,"y":739,"w":180,"h":146},
		"AA0D704B":{"x":249,"y":1,"w":246,"h":201},
		"7F270226":{"x":399,"y":740,"w":178,"h":143},
		"E688D7D":{"x":231,"y":573,"w":200,"h":162},
		"553F4D05":{"x":1328,"y":739,"w":188,"h":152},
		"85AD8584":{"x":1,"y":205,"w":229,"h":184},
		"8ED3AFE8":{"x":689,"y":392,"w":225,"h":176},
		"A7BCCAF":{"x":993,"y":201,"w":236,"h":189},
		"4EECB0C0":{"x":1690,"y":566,"w":219,"h":171},
		"CB7D7700":{"x":1,"y":575,"w":198,"h":161},
		"667F0ED5":{"x":745,"y":1,"w":246,"h":199},
		"49CF2D80":{"x":1485,"y":198,"w":240,"h":191},
		"533B108C":{"x":1730,"y":1,"w":242,"h":194},
		"280EE8E4":{"x":1231,"y":391,"w":228,"h":179},
		"8B05478":{"x":1730,"y":197,"w":241,"h":193},
		"1B338CA3":{"x":1,"y":391,"w":228,"h":182},
		"86D5947A":{"x":1485,"y":1,"w":243,"h":195},
		"34C42683":{"x":916,"y":567,"w":215,"h":170},
		"B36FAE0":{"x":745,"y":202,"w":234,"h":188},
		"123309C6":{"x":1,"y":738,"w":195,"h":157},
		"3911B93D":{"x":201,"y":737,"w":196,"h":158},
		"944E3BD8":{"x":916,"y":392,"w":223,"h":173}
	}}